cirtusai/__init__.py
cirtusai/client.py
cirtusai/exceptions.py
cirtusai/models.py
tests/test_client.py
cirtusai-0.1.1.dist-info/LICENSE
cirtusai-0.1.1.dist-info/METADATA
cirtusai-0.1.1.dist-info/WHEEL
cirtusai-0.1.1.dist-info/top_level.txt
cirtusai-0.1.1.dist-info/RECORD
