Metadata-Version: 2.1
Name: cirtusai
Version: 0.1.1
Summary: Python SDK for interacting with the CirtusAI backend API.
Author: CirtusAI
License: MIT
Project-URL: Homepage, https://cirtusai.com
Project-URL: Repository, https://github.com/CirtusAI/Cirtus-SDK
Keywords: cirtusai,sdk,mail,api,agents,assets
Classifier: Programming Language :: Python :: 3
Classifier: Programming Language :: Python :: 3 :: Only
Classifier: Programming Language :: Python :: 3.10
Classifier: Intended Audience :: Developers
Classifier: Topic :: Software Development :: Libraries
Requires-Python: >=3.10
License-File: LICENSE
Requires-Dist: requests<3.0.0,>=2.32.0
Provides-Extra: dev
Requires-Dist: pytest>=8.0.0; extra == "dev"
